pysedm/__init__.py
pysedm/astrometry.py
pysedm/background.py
pysedm/byecr.py
pysedm/ccd.py
pysedm/contsep.py
pysedm/cubeparser.py
pysedm/flexure.py
pysedm/fluxcalibration.py
pysedm/io.py
pysedm/mapping.py
pysedm/rainbowcam.py
pysedm/sedm.py
pysedm/spectralmatching.py
pysedm/wavesolution.py
pysedm/dask/__init__.py
pysedm/dask/base.py
pysedm/dask/daskec.py
pysedm/dask/daskes.py
pysedm/dask/daskhypergal.py
pysedm/data/KPNO_lines.fits
pysedm/data/alignement_offset.txt
pysedm/data/bad_standard.txt
pysedm/data/cosmicray.txt
pysedm/data/noncalspec_standard.txt
pysedm/script/__init__.py
pysedm/script/calibrate_cube.py
pysedm/script/ccd_to_cube.py
pysedm/utils/__init__.py
pysedm/utils/atmosphere.py
pysedm/utils/hexagrid.py
pysedm/utils/mpl.py
pysedm/utils/pil.py
pysedm/utils/tools.py
pysedm-0.41.0.data/scripts/build_guider.py
pysedm-0.41.0.data/scripts/ccd_to_cube.py
pysedm-0.41.0.data/scripts/cube_quality.py
pysedm-0.41.0.data/scripts/derive_wavesolution.py
pysedm-0.41.0.data/scripts/extract_star.py
pysedm-0.41.0.data/scripts/extractstar.py
pysedm-0.41.0.data/scripts/extractstar_ab.py
pysedm-0.41.0.data/scripts/pysedm_io.py
pysedm-0.41.0.data/scripts/pysedm_pull.py
pysedm-0.41.0.data/scripts/pysedm_report.py
pysedm-0.41.0.data/scripts/quality_check.py
pysedm-0.41.0.data/scripts/rm_cubecr.py
pysedm-0.41.0.dist-info/LICENSE
pysedm-0.41.0.dist-info/METADATA
pysedm-0.41.0.dist-info/WHEEL
pysedm-0.41.0.dist-info/top_level.txt
pysedm-0.41.0.dist-info/RECORD
